[
  {
    "name": "All-Purpose Knife",
    "price": 72.96,
    "isOnSale": false,
    "stock": 8,
    "categoryId": "uncategorized",
    "specifications": [
      "Hidden Tang",
      "Handle: Walnut Wood",
      "Corrosion Resistant",
      "Handle: G10",
      "Spine Thickness: 3 mm"
    ],
    "images": [
      "https://theaceofblades.co.za/wp-content/uploads/AOB-2304-1-100x100.jpg",
      "https://theaceofblades.co.za/wp-content/uploads/AOB-2304-2-100x100.jpg",
      "https://theaceofblades.co.za/wp-content/uploads/AOB-2304-3-100x100.jpg"
    ]
  },
  {
    "name": "Compact Utility Knife",
    "price": 56.64,
    "isOnSale": true,
    "stock": 8,
    "categoryId": "uncategorized",
    "specifications": ["Full Tang", "Hidden Tang", "Finish: Stonewashed"],
    "images": [
      "https://theaceofblades.co.za/wp-content/uploads/woocommerce-placeholder-600x600.png"
    ],
    "newPrice": 42.48
  },
  {
    "name": "Outdoor Edge Knife",
    "price": 39.91,
    "isOnSale": false,
    "stock": 74,
    "categoryId": "collectors",
    "specifications": [
      "Hidden Tang",
      "Grind: Hollow",
      "Blade Length: 3.5 in",
      "HRC 58-60",
      "Blade: 8Cr13MoV",
      "Handle: Micarta"
    ],
    "images": [
      "https://theaceofblades.co.za/wp-content/uploads/aob-2301-3-100x100.jpg",
      "https://theaceofblades.co.za/wp-content/uploads/aob-2301-4-100x100.jpg",
      "https://theaceofblades.co.za/wp-content/uploads/aob-2301-2-100x100.jpg",
      "https://theaceofblades.co.za/wp-content/uploads/aob-2301-1-100x100.jpg"
    ]
  },
  {
    "name": "General Use Knife",
    "price": 96.79,
    "isOnSale": false,
    "stock": 48,
    "categoryId": "collectors",
    "specifications": [
      "Blade: Damascus Steel",
      "Lock: Frame Lock",
      "Handle: G10"
    ],
    "images": [
      "https://theaceofblades.co.za/wp-content/uploads/0006e34b-b96d-4698-8c86-23eb77de8ebd-600x450.jpg"
    ]
  },
  {
    "name": "Multi-Task Knife",
    "price": 85.53,
    "isOnSale": false,
    "stock": 63,
    "categoryId": "collectors",
    "specifications": [
      "Lock: Frame Lock",
      "Blade: Damascus Steel",
      "Weight: 120g"
    ],
    "images": [
      "https://theaceofblades.co.za/wp-content/uploads/2023/06/AOB-2327-3-100x100.jpg",
      "https://theaceofblades.co.za/wp-content/uploads/2023/06/AOB-2327-2-100x100.jpg",
      "https://theaceofblades.co.za/wp-content/uploads/2023/06/AOB-2327-1-100x100.jpg"
    ]
  },
  {
    "name": "Everyday Blade",
    "price": 77.84,
    "isOnSale": true,
    "stock": 10,
    "categoryId": "fixed-blade",
    "specifications": [
      "Dishwasher Safe (Handwash Recommended)",
      "Sheath: Leather",
      "Blade: Damascus Steel",
      "Hidden Tang"
    ],
    "images": [
      "https://theaceofblades.co.za/wp-content/uploads/2023/06/IMG_8568-1-100x100.jpg",
      "https://theaceofblades.co.za/wp-content/uploads/2023/06/IMG_8564-scaled-1-100x100.jpg"
    ],
    "newPrice": 62.27
  },
  {
    "name": "Universal Knife",
    "price": 45.85,
    "isOnSale": false,
    "stock": 51,
    "categoryId": "folding",
    "specifications": [
      "Lock: Liner Lock",
      "Full Tang",
      "Spine Thickness: 3 mm",
      "HRC 58-60"
    ],
    "images": [
      "https://theaceofblades.co.za/wp-content/uploads/aob-2301-3-100x100.jpg",
      "https://theaceofblades.co.za/wp-content/uploads/aob-2301-4-100x100.jpg",
      "https://theaceofblades.co.za/wp-content/uploads/aob-2301-2-100x100.jpg",
      "https://theaceofblades.co.za/wp-content/uploads/aob-2301-1-100x100.jpg"
    ]
  },
  {
    "name": "Damascus Hunter",
    "price": 370.49,
    "isOnSale": false,
    "stock": 73,
    "categoryId": "folding",
    "specifications": [
      "Handle: Micarta",
      "Grind: Hollow",
      "Lock: Frame Lock",
      "HRC 58-60"
    ],
    "images": [
      "https://theaceofblades.co.za/wp-content/uploads/aob-2302-3-100x100.jpg",
      "https://theaceofblades.co.za/wp-content/uploads/aob-2302-1-100x100.jpg"
    ]
  },
  {
    "name": "Limited Edition Bowie",
    "price": 248.71,
    "isOnSale": false,
    "stock": 9,
    "categoryId": "key-rings",
    "specifications": [
      "Lock: Frame Lock",
      "HRC 58-60",
      "Blade: Damascus Steel",
      "Full Tang",
      "Blade Length: 3.5 in"
    ],
    "images": [
      "https://theaceofblades.co.za/wp-content/uploads/2023/06/AOB-2502-600x600.jpg"
    ]
  },
  {
    "name": "Mosaic Damascus Folder",
    "price": 445.4,
    "isOnSale": false,
    "stock": 63,
    "categoryId": "kitchen",
    "specifications": [
      "HRC 58-60",
      "Handle: Walnut Wood",
      "Hidden Tang",
      "Corrosion Resistant"
    ],
    "images": [
      "https://theaceofblades.co.za/wp-content/uploads/IMG_1831-100x100.jpg",
      "https://theaceofblades.co.za/wp-content/uploads/IMG_1748-100x100.jpg"
    ]
  },
  {
    "name": "Artisan Carved Handle",
    "price": 299.82,
    "isOnSale": false,
    "stock": 33,
    "categoryId": "kitchen",
    "specifications": [
      "Finish: Stonewashed",
      "Finish: Satin",
      "Blade: Damascus Steel",
      "Dishwasher Safe (Handwash Recommended)"
    ],
    "images": [
      "https://theaceofblades.co.za/wp-content/uploads/2023/06/Knives-0822-9-scaled-1-600x600.jpg"
    ]
  },
  {
    "name": "Antique Finish Dagger",
    "price": 225.85,
    "isOnSale": false,
    "stock": 25,
    "categoryId": "kitchen",
    "specifications": [
      "Blade Length: 8 in",
      "Blade: Damascus Steel",
      "Lock: Frame Lock",
      "Non-slip Handle",
      "Dishwasher Safe (Handwash Recommended)",
      "Grind: Hollow"
    ],
    "images": [
      "https://theaceofblades.co.za/wp-content/uploads/2023/06/2410-1-600x600.jpg"
    ]
  },
  {
    "name": "Exhibition Grade Kukri",
    "price": 384.51,
    "isOnSale": false,
    "stock": 73,
    "categoryId": "knife-care",
    "specifications": [
      "Dishwasher Safe (Handwash Recommended)",
      "Overall Length: 8.2 in",
      "Sheath: Kydex",
      "Handle: G10",
      "Sheath: Leather"
    ],
    "images": [
      "https://theaceofblades.co.za/wp-content/uploads/2023/06/0420222-600x600.jpg"
    ]
  },
  {
    "name": "Exhibition Grade Kukri",
    "price": 384.51,
    "isOnSale": false,
    "stock": 73,
    "categoryId": "straight-razors",
    "specifications": [
      "Dishwasher Safe (Handwash Recommended)",
      "Overall Length: 8.2 in",
      "Sheath: Kydex",
      "Handle: G10",
      "Sheath: Leather"
    ],
    "images": [
      "https://theaceofblades.co.za/wp-content/uploads/20-100x100.jpg",
      "https://theaceofblades.co.za/wp-content/uploads/21-100x100.jpg"
    ]
  }
]
